Random_Arithmetic_question/Random_Arithmetic_question.py
Random_Arithmetic_question/__init__.py
Random_Arithmetic_question-0.0.dist-info/METADATA
Random_Arithmetic_question-0.0.dist-info/WHEEL
Random_Arithmetic_question-0.0.dist-info/top_level.txt
Random_Arithmetic_question-0.0.dist-info/RECORD
