Metadata-Version: 2.1
Name: Random-Arithmetic-question
Version: 0.0
Summary: Random Arithmetic Question
Author-email: dharmisha2207@gmail.com
